MANIFEST.in
README.md
pyproject.toml
setup.py
amuse_secularmultiple.egg-info/PKG-INFO
amuse_secularmultiple.egg-info/SOURCES.txt
amuse_secularmultiple.egg-info/dependency_links.txt
amuse_secularmultiple.egg-info/requires.txt
amuse_secularmultiple.egg-info/top_level.txt
src/amuse/community/secularmultiple/Makefile
src/amuse/community/secularmultiple/__init__.py
src/amuse/community/secularmultiple/_version.py
src/amuse/community/secularmultiple/interface.cpp
src/amuse/community/secularmultiple/interface.h
src/amuse/community/secularmultiple/interface.py
src/amuse/community/secularmultiple/readme.txt
src/amuse/community/secularmultiple/src/ODE_system.cpp
src/amuse/community/secularmultiple/src/ODE_system.h
src/amuse/community/secularmultiple/src/evolve.cpp
src/amuse/community/secularmultiple/src/evolve.h
src/amuse/community/secularmultiple/src/external.cpp
src/amuse/community/secularmultiple/src/external.h
src/amuse/community/secularmultiple/src/newtonian.cpp
src/amuse/community/secularmultiple/src/newtonian.h
src/amuse/community/secularmultiple/src/postnewtonian.cpp
src/amuse/community/secularmultiple/src/postnewtonian.h
src/amuse/community/secularmultiple/src/root_finding.cpp
src/amuse/community/secularmultiple/src/root_finding.h
src/amuse/community/secularmultiple/src/structure.cpp
src/amuse/community/secularmultiple/src/structure.h
src/amuse/community/secularmultiple/src/tides.cpp
src/amuse/community/secularmultiple/src/tides.h
src/amuse/community/secularmultiple/src/types.cpp
src/amuse/community/secularmultiple/src/types.h
src/amuse/community/secularmultiple/src/cvode/cvode.c
src/amuse/community/secularmultiple/src/cvode/cvode.h
src/amuse/community/secularmultiple/src/cvode/cvode_dense.c
src/amuse/community/secularmultiple/src/cvode/cvode_dense.h
src/amuse/community/secularmultiple/src/cvode/cvode_direct.c
src/amuse/community/secularmultiple/src/cvode/cvode_direct.h
src/amuse/community/secularmultiple/src/cvode/cvode_direct_impl.h
src/amuse/community/secularmultiple/src/cvode/cvode_impl.h
src/amuse/community/secularmultiple/src/cvode/cvode_io.c
src/amuse/community/secularmultiple/src/cvode/nvector_serial.c
src/amuse/community/secularmultiple/src/cvode/nvector_serial.h
